{"meta": {"strings": {"owl.live-match.upcoming": "\u5373\u5c06\u76f4\u64ad", "owl.live-stream.game-of": "\u6bd4\u8d5b\uff1a##/##", "owl.live-stream.view-more": "\u67e5\u770b\u66f4\u591a", "owl.live-match.now": "\u6b63\u5728\u76f4\u64ad", "owl.live-stream.game": "\u7b2c##\u5c40", "owl.live-stream.results": "\u8d5b\u51b5", "owl.rewards.info.description.logged-in": "\u60a8\u5df2\u767b\u5f55\uff0c\u6b22\u8fce\u9886\u53d6<a href=\"{0}\">\u89c2\u8d5b\u5956\u52b1</a>\u3002\u4ec5\u9002\u7528\u4e8e\u90e8\u5206\u5730\u533a\u3002", "owl.live-stream.phoenix-disclaimer": "\u6b22\u8fce\u524d\u5f80<a rel=\"external\" href=\"https://www.overwatchleague.cn\">overwatchleague.cn</a>\u89c2\u770b\u66f4\u9ad8\u753b\u8d28\u89c6\u9891\u3002", "owl.rewards.info.description": "<a href=\"{0}\">\u7acb\u5373\u767b\u5f55</a>\u4ee5\u9886\u53d6\u89c2\u8d5b\u5956\u52b1\u3002 <a href=\"{1}\">\u4ec5\u9002\u7528\u4e8e\u90e8\u5206\u5730\u533a </a>\u3002", "owl.live-stream.view-less": "\u6536\u8d77"}}, "data": {"liveMatch": {"clientHints": [], "liveStatus": "UPCOMING", "scores": [{"value": 0}, {"value": 0}], "competitors": [{"availableLanguages": ["en", "it", "ru", "ja", "zh-cn", "th", "ko", "es-mx", "pt", "fr", "zh-tw"], "logo": "https://bnetcmsus-a.akamaihd.net/cms/page_media/3JZTLCPH37QD1508792362853.png", "secondaryColor": "000000", "secondaryPhoto": "https://bnetcmsus-a.akamaihd.net/cms/template_resource/LAKZ6R7QEG6S1507822883033.svg", "id": 4524, "addressCountry": "US", "content": {"description": "We're excited to announce the Philadelphia Fusion, a team whose name and logo reflect the velocity, dynamism, and creative energy that is generated by bringing distinct parts together to produce something new. The orange and black of the Fusion's team colors have a special place in the heart of Philadelphia sports fans, as they are also the official colors of the professional ice hockey team known as the Philadelphia Flyers (which is also owned by the Fusion's parent company).", "colors": [{"usage": "primary", "color": {"color": "#FF9E1B", "opacity": 1}, "name": "Philadelphia Orange"}, {"usage": "secondary", "color": {"color": "#000000", "opacity": 1}, "name": "Philadelphia Black"}, {"usage": "tertiary", "color": {"color": "#FFFFFF", "opacity": 1}, "name": "Philadelphia White"}], "icons": [{"usage": "main", "png": "https://bnetcmsus-a.akamaihd.net/cms/page_media/3JZTLCPH37QD1508792362853.png", "svg": "https://bnetcmsus-a.akamaihd.net/cms/template_resource/LAKZ6R7QEG6S1507822883033.svg"}, {"usage": "alt", "png": "https://bnetcmsus-a.akamaihd.net/cms/page_media/I27PIIZ50XTD1512520986476.png", "svg": "https://bnetcmsus-a.akamaihd.net/cms/page_media/ZCXZIQT5S9AA1512520986491.svg"}, {"usage": "mainName", "png": "https://bnetcmsus-a.akamaihd.net/cms/page_media/9ET6XW6MVT3L1519747890823.svg", "svg": "https://bnetcmsus-a.akamaihd.net/cms/page_media/9ET6XW6MVT3L1519747890823.svg"}], "id": 4524, "location": "Philadelphia", "teamWebsite": "https://fusion.overwatchleague.com", "nid": 13, "abbreviatedName": "PF", "logoLockup": "https://fusion.overwatchleague.com", "name": "Fusion"}, "icon": "https://bnetcmsus-a.akamaihd.net/cms/template_resource/LAKZ6R7QEG6S1507822883033.svg", "primaryColor": "ff9e1b", "homeLocation": "\u5bbe\u5915\u6cd5\u5c3c\u4e9a\u5dde\uff0c\u8d39\u57ce", "handle": "fusion.2056", "type": "TEAM", "abbreviatedName": "PHI", "game": "OVERWATCH", "name": "\u8d39\u57ce\u878d\u5408\u961f"}, {"availableLanguages": ["en", "zh-tw", "it", "ru", "ja", "zh-cn", "th", "ko", "es-es", "es-mx", "pt"], "logo": "https://bnetcmsus-a.akamaihd.net/cms/page_media/LHRSIW3NWH211508792362796.png", "secondaryColor": "000000", "secondaryPhoto": "https://bnetcmsus-a.akamaihd.net/cms/page_media/E9MU0AK0JIXT1507858876249.svg", "id": 4409, "addressCountry": "KR", "content": {"description": "While the name certainly evokes images of Asian rulers in bygone eras, it's also a term in traditional sports, reserved only for those teams whose names become indelibly associated with long-term success\u2014a distinction this team is clearly aiming for. As for the logo, the tiger is a national symbol of South Korea, representing strength, courage, and good fortune, while the golden color emphasizes the connection to royalty.", "colors": [{"usage": "secondary", "color": {"color": "#AA8A00", "opacity": 1}, "name": "Dynasty Gold"}, {"usage": "primary", "color": {"color": "#000000", "opacity": 1}, "name": "Dynasty Black"}, {"usage": "tertiary", "color": {"color": "#FFFFFF", "opacity": 1}, "name": "Dynasty White"}], "icons": [{"usage": "main", "png": "https://bnetcmsus-a.akamaihd.net/cms/page_media/LHRSIW3NWH211508792362796.png", "svg": "https://bnetcmsus-a.akamaihd.net/cms/page_media/E9MU0AK0JIXT1507858876249.svg"}, {"usage": "mainName", "png": "https://bnetcmsus-a.akamaihd.net/cms/page_media/PALRGLF8SMMC1519747890813.svg", "svg": "https://bnetcmsus-a.akamaihd.net/cms/page_media/PALRGLF8SMMC1519747890813.svg"}], "id": 4409, "location": "Seoul", "teamWebsite": "https://dynasty.overwatchleague.com", "nid": 9, "abbreviatedName": "SEO", "logoLockup": "https://dynasty.overwatchleague.com", "name": "Dynasty"}, "icon": "https://bnetcmsus-a.akamaihd.net/cms/page_media/E9MU0AK0JIXT1507858876249.svg", "primaryColor": "aa8a00", "homeLocation": "\u97e9\u56fd\uff0c\u9996\u5c14", "handle": "seoul.1029", "type": "TEAM", "abbreviatedName": "SEO", "game": "OVERWATCH", "name": "\u9996\u5c14\u738b\u671d\u961f"}], "conclusionValue": 4, "games": [{"state": "PENDING", "attributes": {"map": "volskaya", "mapGuid": "0x08000000000001DB"}, "number": 1, "attributesVersion": "0.1.0", "stats": null, "id": 6034}, {"state": "PENDING", "attributes": {"map": "lijiang", "mapGuid": "0x0800000000000662"}, "number": 2, "attributesVersion": "0.2.0", "stats": null, "id": 6035}, {"state": "PENDING", "attributes": {"map": "kings-row", "mapGuid": "0x08000000000000D4"}, "number": 3, "attributesVersion": "0.2.0", "stats": null, "id": 6943}, {"state": "PENDING", "attributes": {"map": "gibraltar", "mapGuid": "0x0800000000000184"}, "number": 4, "attributesVersion": "0.2.0", "stats": null, "id": 6036}], "videos": [], "bracket": {"clientHints": [], "winners": 1, "teamSize": 6, "stage": {"title": "Stage 2", "availableLanguages": ["en"], "id": 4667, "tournament": {"series": {"id": 55}, "availableLanguages": ["en"], "featured": false, "location": "Burbank, CA", "title": "Overwatch League - Stage 2", "draft": false, "handle": "tournament-650ec193-0ae6-2c4a-95c6-0296269b3746", "id": 3831, "game": "OVERWATCH"}}, "allowDraw": false, "repeatableMatchUps": 0, "matchConclusionValue": 4, "id": 2727, "thirdPlaceMatch": false, "advantageComparing": "AFTER_MATCH", "matchConclusionStrategy": "MINIMUM", "type": "OPEN_MATCH"}, "attributes": {}, "startDateTS": 1520553600000, "youtubeId": "", "dateCreated": 1507007199503, "handle": "match-de7231ef-d7f1-8547-ada4-da7bc9cafa6e", "conclusionStrategy": "MINIMUM", "state": "PENDING", "endDateTS": 1520560800000, "id": 10305, "endDate": "2018-03-09T02:00:00.000Z", "losses": [0, 0], "showStartTime": true, "ties": [0, 0], "startDate": "2018-03-09T00:00:00.000Z", "wins": [0, 0], "flags": [], "timeToMatch": 2979515, "showEndTime": true}, "nextMatch": {}}}