{"data": {"liveMatch": {"flags": [], "clientHints": [], "dateCreated": 1507007199508, "attributes": {}, "startDate": "2018-03-17T20:00:00.000Z", "state": "PENDING", "youtubeId": "", "wins": [1, 3], "startDateTS": 1521316800000, "handle": "match-bf3c7d92-8135-b046-bcf9-2b903f81de59", "conclusionValue": 4, "ties": [0, 0], "showStartTime": true, "scores": [{"value": 0}, {"value": 3}], "timeToMatch": 6021172, "competitors": [{"homeLocation": "\u97e9\u56fd\uff0c\u9996\u5c14", "icon": "https://bnetcmsus-a.akamaihd.net/cms/page_media/E9MU0AK0JIXT1507858876249.svg", "primaryColor": "aa8a00", "secondaryPhoto": "https://bnetcmsus-a.akamaihd.net/cms/page_media/E9MU0AK0JIXT1507858876249.svg", "id": 4409, "logo": "https://bnetcmsus-a.akamaihd.net/cms/page_media/LHRSIW3NWH211508792362796.png", "abbreviatedName": "SEO", "availableLanguages": ["en", "zh-tw", "it", "ru", "ja", "zh-cn", "th", "ko", "es-es", "es-mx", "pt"], "secondaryColor": "000000", "content": {"logoLockup": "https://dynasty.overwatchleague.com", "icons": [{"svg": "https://bnetcmsus-a.akamaihd.net/cms/page_media/E9MU0AK0JIXT1507858876249.svg", "usage": "main", "png": "https://bnetcmsus-a.akamaihd.net/cms/page_media/LHRSIW3NWH211508792362796.png"}, {"svg": "https://bnetcmsus-a.akamaihd.net/cms/page_media/PALRGLF8SMMC1519747890813.svg", "usage": "mainName", "png": "https://bnetcmsus-a.akamaihd.net/cms/page_media/PALRGLF8SMMC1519747890813.svg"}], "colors": [{"color": {"opacity": 1, "color": "#AA8A00"}, "usage": "secondary", "name": "Dynasty Gold"}, {"color": {"opacity": 1, "color": "#000000"}, "usage": "primary", "name": "Dynasty Black"}, {"color": {"opacity": 1, "color": "#FFFFFF"}, "usage": "tertiary", "name": "Dynasty White"}], "name": "Dynasty", "description": "While the name certainly evokes images of Asian rulers in bygone eras, it's also a term in traditional sports, reserved only for those teams whose names become indelibly associated with long-term success\u2014a distinction this team is clearly aiming for. As for the logo, the tiger is a national symbol of South Korea, representing strength, courage, and good fortune, while the golden color emphasizes the connection to royalty.", "nid": 9, "teamWebsite": "https://dynasty.overwatchleague.com", "id": 4409, "location": "Seoul", "abbreviatedName": "SEO"}, "name": "\u9996\u5c14\u738b\u671d\u961f", "type": "TEAM", "game": "OVERWATCH", "handle": "seoul.1029", "addressCountry": "KR"}, {"homeLocation": "\u82f1\u683c\u5170\uff0c\u4f26\u6566", "icon": "https://bnetcmsus-a.akamaihd.net/cms/template_resource/HCS229B4DP021507822883016.svg", "primaryColor": "ff8200", "secondaryPhoto": "https://bnetcmsus-a.akamaihd.net/cms/template_resource/HCS229B4DP021507822883016.svg", "id": 4410, "logo": "https://bnetcmsus-a.akamaihd.net/cms/page_media/NW461AQIYQMK1508792363133.png", "abbreviatedName": "LDN", "availableLanguages": ["en", "ru", "ja", "zh-cn", "th", "ko", "es-es", "es-mx", "pt", "zh-tw", "fr", "it"], "secondaryColor": "59cbe8", "content": {"logoLockup": "https://spitfire.overwatchleague.com", "icons": [{"svg": "https://bnetcmsus-a.akamaihd.net/cms/template_resource/HCS229B4DP021507822883016.svg", "usage": "main", "png": "https://bnetcmsus-a.akamaihd.net/cms/page_media/NW461AQIYQMK1508792363133.png"}, {"svg": "https://bnetcmsus-a.akamaihd.net/cms/page_media/9X0RTOLWRG231519747890764.svg", "usage": "mainName", "png": "https://bnetcmsus-a.akamaihd.net/cms/page_media/9X0RTOLWRG231519747890764.svg"}], "colors": [{"color": {"opacity": 1, "color": "#FF8200"}, "usage": "primary", "name": "London Orange (switched for engineering needs)"}, {"color": {"opacity": 1, "color": "#59CBE8"}, "usage": "secondary", "name": "London Blue (switched for engineering needs)"}, {"color": {"opacity": 1, "color": "#1C2B39"}, "usage": "tertiary", "name": "London Navy (switched for engineering needs)"}], "name": "Spitfire", "description": "The Supermarine Spitfire was the name of a British fighter plane that was flown in the Royal Air Force, most famously during the Battle of Britain in World War II, and it is this spirit of bravery under fire that imbues the team's identity. The light blue of the logo's background is the blue of Cloud9, London Spitfire\u2019s parent organization, which has a storied history in Western esports. The Spitfire itself and the orange of the team's colors are a nod to Lena \u201cTracer\u201d Oxton, the British Overwatch\u00ae hero who was a member of the RAF in the game\u2019s lore.", "nid": 12, "teamWebsite": "https://spitfire.overwatchleague.com", "id": 4410, "location": "London", "abbreviatedName": "LS"}, "name": "\u4f26\u6566\u55b7\u706b\u6218\u6597\u673a\u961f", "type": "TEAM", "game": "OVERWATCH", "handle": "london.6950", "addressCountry": "GB"}], "conclusionStrategy": "MINIMUM", "bracket": {"teamSize": 6, "matchConclusionValue": 4, "id": 2727, "type": "OPEN_MATCH", "allowDraw": false, "matchConclusionStrategy": "MINIMUM", "winners": 1, "thirdPlaceMatch": false, "repeatableMatchUps": 0, "stage": {"availableLanguages": ["en"], "title": "Stage 2", "id": 4667, "tournament": {"availableLanguages": ["en"], "game": "OVERWATCH", "featured": false, "draft": false, "title": "Overwatch League - Stage 2", "handle": "tournament-650ec193-0ae6-2c4a-95c6-0296269b3746", "id": 3831, "location": "Burbank, CA", "series": {"id": 55}}}, "advantageComparing": "AFTER_MATCH", "clientHints": []}, "id": 10323, "liveStatus": "LIVE", "endDate": "2018-03-17T22:00:00.000Z", "games": [{"attributes": {"mapGuid": "0x0800000000000165", "map": "hanamura", "instanceID": "06c00f0a16ed0002:02ca57c148da026e", "mapScore": {"team2": 4, "team1": 3}}, "number": 1, "attributesVersion": "0.2.0", "points": [3, 4], "state": "CONCLUDED", "handle": "matchgame-b77b11f0-0dc3-da48-8f11-ae1f66b44b6f", "id": 6098, "stats": null}, {"attributes": {"mapGuid": "0x0800000000000662", "map": "lijiang", "instanceID": "06c00f0a16ed0002:02cb85411c670282", "mapScore": {"team2": 2, "team1": 0}}, "number": 2, "attributesVersion": "0.2.0", "points": [0, 2], "state": "CONCLUDED", "handle": "matchgame-c278730f-731e-e94e-a878-8b7be1f8c55b", "id": 6099, "stats": null}, {"attributes": {"mapGuid": "0x08000000000000D4", "map": "kings-row", "instanceID": "06c00f0a16ed0002:02cbc282924a0283", "mapScore": {"team2": 3, "team1": 2}}, "number": 3, "attributesVersion": "0.2.0", "points": [2, 3], "state": "CONCLUDED", "handle": "matchgame-d9bd892b-51d4-5943-95bd-43740fd26f97", "id": 6951, "stats": null}, {"attributes": {"mapGuid": "0x0800000000000184", "map": "gibraltar", "instanceID": "06c00f0a16ed0002:02cc355753540284", "mapScore": {"team2": 0, "team1": 2}}, "number": 4, "attributesVersion": "0.2.0", "points": [2, 0], "state": "IN_PROGRESS", "handle": "matchgame-41b297e5-29bb-a844-839b-ae5a2f252233", "id": 6100, "stats": null}], "videos": [{"youtubeId": "", "thumbnailUrl": "", "description": "", "name": 1, "vodLink": ""}, {"youtubeId": "", "thumbnailUrl": "", "description": "", "name": 2, "vodLink": ""}, {"youtubeId": "", "thumbnailUrl": "", "description": "", "name": 3, "vodLink": ""}, {"youtubeId": "", "thumbnailUrl": "", "description": "", "name": 4, "vodLink": ""}], "losses": [3, 1], "showEndTime": true, "endDateTS": 1521324000000}, "nextMatch": {"flags": [], "clientHints": [], "dateCreated": 1507007199508, "attributes": {}, "startDate": "2018-03-17T22:00:00.000Z", "state": "PENDING", "youtubeId": "", "wins": [0, 0], "startDateTS": 1521324000000, "handle": "match-6c48fa19-eba8-7d4e-ad37-0644bbe2a341", "conclusionValue": 4, "ties": [0, 0], "showStartTime": true, "scores": [{"value": 0}, {"value": 0}], "timeToMatch": 1178828, "competitors": [{"homeLocation": "\u52a0\u5229\u798f\u5c3c\u4e9a\u5dde\uff0c\u65e7\u91d1\u5c71", "icon": "https://bnetcmsus-a.akamaihd.net/cms/template_resource/0SY7LHKHV86R1507822883113.svg", "primaryColor": "fc4c02", "secondaryPhoto": "https://bnetcmsus-a.akamaihd.net/cms/template_resource/0SY7LHKHV86R1507822883113.svg", "id": 4404, "logo": "https://bnetcmsus-a.akamaihd.net/cms/page_media/YO24NN5KAOFL1508792362791.png", "abbreviatedName": "SFS", "availableLanguages": ["en", "zh-tw", "zh-cn", "th", "ko", "ru", "ja", "pt"], "secondaryColor": "75787b", "content": {"logoLockup": "https://shock.overwatchleague.com", "icons": [{"svg": "https://bnetcmsus-a.akamaihd.net/cms/template_resource/0SY7LHKHV86R1507822883113.svg", "usage": "main", "png": "https://bnetcmsus-a.akamaihd.net/cms/page_media/YO24NN5KAOFL1508792362791.png"}, {"svg": "https://bnetcmsus-a.akamaihd.net/cms/page_media/PKGNG1U3MGZ71512520986545.svg", "usage": "alt", "png": "https://bnetcmsus-a.akamaihd.net/cms/page_media/JIE3PV2FOMB81512520986533.png"}, {"svg": "https://bnetcmsus-a.akamaihd.net/cms/page_media/A3LMQCXG0UR11519747890866.svg", "usage": "mainName", "png": "https://bnetcmsus-a.akamaihd.net/cms/page_media/A3LMQCXG0UR11519747890866.svg"}], "colors": [{"color": {"opacity": 1, "color": "#FC4C02"}, "usage": "primary", "name": "Shock Orange"}, {"color": {"opacity": 1, "color": "#75787B"}, "usage": "secondary", "name": "Shock Gray"}, {"color": {"opacity": 1, "color": "#CAB64B"}, "usage": "tertiary", "name": "Shock Gold"}], "name": "Shock", "description": "The Shock's logo references parts of San Francisco's past and present that are as vivacious as the bright orange of the city's famous Golden Gate Bridge. The seismograph waves and the name evoke the region's earthquake activity, while its gold color hearkens back to San Francisco's origins in the California gold rush of the 1800s.", "nid": 7, "teamWebsite": "https://shock.overwatchleague.com", "id": 4404, "location": "San Francisco", "abbreviatedName": "SFS"}, "name": "\u65e7\u91d1\u5c71\u9707\u52a8\u961f", "type": "TEAM", "game": "OVERWATCH", "handle": "san-francisco.3862", "addressCountry": "US"}, {"homeLocation": "\u5fb7\u514b\u8428\u65af\u5dde\uff0c\u4f11\u65af\u987f", "icon": "https://bnetcmsus-a.akamaihd.net/cms/page_media/UPM8U5QV3DDU1507858876250.svg", "primaryColor": "000000", "secondaryPhoto": "https://bnetcmsus-a.akamaihd.net/cms/page_media/UPM8U5QV3DDU1507858876250.svg", "id": 4525, "logo": "https://bnetcmsus-a.akamaihd.net/cms/page_media/HLRHYU5MT9MD1508792362935.png", "abbreviatedName": "HOU", "availableLanguages": ["en", "ko", "ru", "ja", "zh-tw", "zh-cn", "th"], "secondaryColor": "97d700", "content": {"logoLockup": "https://outlaws.overwatchleague.com", "icons": [{"svg": "https://bnetcmsus-a.akamaihd.net/cms/page_media/UPM8U5QV3DDU1507858876250.svg", "usage": "main", "png": "https://bnetcmsus-a.akamaihd.net/cms/page_media/HLRHYU5MT9MD1508792362935.png"}, {"svg": "https://bnetcmsus-a.akamaihd.net/cms/page_media/LTMO2GQOW9FK1516299021322.svg", "usage": "alt", "png": "https://bnetcmsus-a.akamaihd.net/cms/page_media/MRM2W1KHOVAF1516299155079.png"}, {"svg": "https://bnetcmsus-a.akamaihd.net/cms/page_media/5LE7DCUS8ORD1519747890767.svg", "usage": "mainName", "png": "https://bnetcmsus-a.akamaihd.net/cms/page_media/5LE7DCUS8ORD1519747890767.svg"}], "colors": [{"color": {"opacity": 1, "color": "#000000"}, "usage": "secondary", "name": "Houston Black"}, {"color": {"opacity": 1, "color": "#97D700"}, "usage": "primary", "name": "Houston Green"}, {"color": {"opacity": 1, "color": "#FFFFFF"}, "usage": "tertiary", "name": "Houston White"}], "name": "Outlaws", "description": "Texas is famous for its hardy, self-reliant cowboy culture, where people live by their own rules. The team name references this rebellious streak, and the star, longhorn skull, and twin revolvers in the team logo are also emblematic of the Lone Star State. Last but not least, the green in the team's colors is a signature shade for Outlaws parent organization OpTic Gaming, whose rabid fans are collectively known as \"the Green Wall.\"", "nid": 10, "teamWebsite": "https://outlaws.overwatchleague.com", "id": 4525, "location": "Houston", "abbreviatedName": "HO"}, "name": "\u4f11\u65af\u987f\u795e\u67aa\u624b\u961f", "type": "TEAM", "game": "OVERWATCH", "handle": "houston.4749", "addressCountry": "US"}], "conclusionStrategy": "MINIMUM", "bracket": {"teamSize": 6, "matchConclusionValue": 4, "id": 2727, "type": "OPEN_MATCH", "allowDraw": false, "matchConclusionStrategy": "MINIMUM", "winners": 1, "thirdPlaceMatch": false, "repeatableMatchUps": 0, "stage": {"availableLanguages": ["en"], "title": "Stage 2", "id": 4667, "tournament": {"availableLanguages": ["en"], "game": "OVERWATCH", "featured": false, "draft": false, "title": "Overwatch League - Stage 2", "handle": "tournament-650ec193-0ae6-2c4a-95c6-0296269b3746", "id": 3831, "location": "Burbank, CA", "series": {"id": 55}}}, "advantageComparing": "AFTER_MATCH", "clientHints": []}, "id": 10324, "liveStatus": "UPCOMING", "endDate": "2018-03-18T00:00:00.000Z", "games": [{"attributes": {"mapGuid": "0x0800000000000165", "map": "hanamura"}, "number": 1, "attributesVersion": "0.1.0", "state": "PENDING", "id": 6101, "stats": null}, {"attributes": {"mapGuid": "0x08000000000004B7", "map": "nepal"}, "number": 2, "attributesVersion": "0.2.0", "state": "PENDING", "id": 6102, "stats": null}, {"attributes": {"mapGuid": "0x08000000000002AF", "map": "hollywood"}, "number": 3, "attributesVersion": "0.2.0", "state": "PENDING", "id": 6103, "stats": null}, {"attributes": {"mapGuid": "0x0800000000000184", "map": "gibraltar"}, "number": 4, "attributesVersion": "0.2.0", "state": "PENDING", "id": 6104, "stats": null}], "videos": [], "losses": [0, 0], "showEndTime": true, "endDateTS": 1521331200000}}, "meta": {"strings": {"owl.live-stream.view-less": "\u6536\u8d77", "owl.rewards.info.description.logged-in": "\u60a8\u5df2\u767b\u5f55\uff0c\u6b22\u8fce\u9886\u53d6<a href=\"{0}\">\u89c2\u8d5b\u5956\u52b1</a>\u3002\u4ec5\u9002\u7528\u4e8e\u90e8\u5206\u5730\u533a\u3002", "owl.live-match.now": "\u6b63\u5728\u76f4\u64ad", "owl.live-stream.game": "\u7b2c##\u5c40", "owl.live-stream.phoenix-disclaimer": "\u6b22\u8fce\u524d\u5f80<a rel=\"external\" href=\"https://www.overwatchleague.cn\">overwatchleague.cn</a>\u89c2\u770b\u66f4\u9ad8\u753b\u8d28\u89c6\u9891\u3002", "owl.live-stream.game-of": "\u6bd4\u8d5b\uff1a##/##", "owl.live-match.upcoming": "\u5373\u5c06\u76f4\u64ad", "owl.rewards.info.description": "<a href=\"{0}\">\u7acb\u5373\u767b\u5f55</a>\u4ee5\u9886\u53d6\u89c2\u8d5b\u5956\u52b1\u3002 <a href=\"{1}\">\u4ec5\u9002\u7528\u4e8e\u90e8\u5206\u5730\u533a </a>\u3002", "owl.live-stream.view-more": "\u67e5\u770b\u66f4\u591a", "owl.live-stream.results": "\u8d5b\u51b5"}}}